medplexity/__init__.py
medplexity/benchmarks/__init__.py
medplexity/benchmarks/dataset_builder.py
medplexity/benchmarks/dataset_factory.py
medplexity/benchmarks/healthsearchqa/__init__.py
medplexity/benchmarks/healthsearchqa/healthsearchqa_dataset_builder.py
medplexity/benchmarks/healthsearchqa/models.py
medplexity/benchmarks/loaders.py
medplexity/benchmarks/medicationqa/__init__.py
medplexity/benchmarks/medicationqa/medicationqa_dataset_builder.py
medplexity/benchmarks/medicationqa/models.py
medplexity/benchmarks/medmcqa/__init__.py
medplexity/benchmarks/medmcqa/examples.json
medplexity/benchmarks/medmcqa/medmcqa_dataset_builder.py
medplexity/benchmarks/medmcqa/models.py
medplexity/benchmarks/medqa/__init__.py
medplexity/benchmarks/medqa/examples.json
medplexity/benchmarks/medqa/medqa_dataset_builder.py
medplexity/benchmarks/medqa/models.py
medplexity/benchmarks/mmlu/__init__.py
medplexity/benchmarks/mmlu/examples.json
medplexity/benchmarks/mmlu/mmlu_dataset_builder.py
medplexity/benchmarks/mmlu/models.py
medplexity/benchmarks/mts_dialog/__init__.py
medplexity/benchmarks/mts_dialog/models.py
medplexity/benchmarks/mts_dialog/mts_dialog_dataset_builder.py
medplexity/benchmarks/multiple_choice_utils.py
medplexity/benchmarks/pubmedqa/__init__.py
medplexity/benchmarks/pubmedqa/examples.json
medplexity/benchmarks/pubmedqa/models.py
medplexity/benchmarks/pubmedqa/pubmedqa_dataset_builder.py
medplexity/benchmarks/utils.py
medplexity/benchmarks/vqa_utils.py
medplexity/benchmarks/vqarad/__init__.py
medplexity/benchmarks/vqarad/models.py
medplexity/benchmarks/vqarad/vqarad_dataset_builder.py
medplexity/chains/chain.py
medplexity/chains/evaluation_adapter_chain.py
medplexity/chains/langchain_wrapper.py
medplexity/chains/llm_chain.py
medplexity/chains/multiple_choice_question_chain.py
medplexity/chains/summarisation_chain.py
medplexity/chains/vqa_chain.py
medplexity/datasets/dataset.py
medplexity/evaluators/evaluation_summary.py
medplexity/evaluators/evaluator.py
medplexity-0.1.6.dist-info/LICENSE
medplexity-0.1.6.dist-info/METADATA
medplexity-0.1.6.dist-info/WHEEL
medplexity-0.1.6.dist-info/RECORD
