Metadata-Version: 2.1
Name: medplexity
Version: 0.1.6
Summary: medplexity helps with evaluation of LLMs for medical use-cases.
License: MIT
Author: MaksymPetyak
Author-email: petyak.mi@gmail.com
Requires-Python: >=3.10,<4.0
Classifier: License :: OSI Approved :: MIT License
Classifier: Programming Language :: Python :: 3
Classifier: Programming Language :: Python :: 3.10
Classifier: Programming Language :: Python :: 3.11
Provides-Extra: google-search-results
Provides-Extra: langchain
Provides-Extra: supabase
Requires-Dist: datasets (>=2.14.5,<3.0.0)
Requires-Dist: google-search-results (>=2.4.2,<3.0.0) ; extra == "google-search-results"
Requires-Dist: langchain (>=0.0.306,<0.0.307) ; extra == "langchain"
Requires-Dist: openai (>=1.3.3,<2.0.0)
Requires-Dist: pillow (>=10.1.0,<11.0.0)
Requires-Dist: pydantic (>=2.3.0,<3.0.0)
Requires-Dist: python-dotenv (>=1.0.0,<2.0.0)
Requires-Dist: supabase (>=2.0.3,<3.0.0) ; extra == "supabase"
